single_sample_gsea/__init__.py
single_sample_gsea/ssgsea.py
single_sample_gsea-0.2.0.dist-info/LICENSE
single_sample_gsea-0.2.0.dist-info/METADATA
single_sample_gsea-0.2.0.dist-info/WHEEL
single_sample_gsea-0.2.0.dist-info/top_level.txt
single_sample_gsea-0.2.0.dist-info/RECORD
