Metadata-Version: 2.1
Name: single-sample-gsea
Version: 0.2.0
Summary: Single Sample GSEA
Author: Jaka Kokošar, Martin Špendl, Ela Praznik
Maintainer: Jaka Kokošar
License: Apache License
Project-URL: Homepage, https://github.com/jakakokosar/ssGSEA
Project-URL: Bug Reports, https://github.com/jakakokosar/ssGSEAissues
Project-URL: Source, https://github.com/jakakokosar/ssGSEA
Classifier: Development Status :: 3 - Alpha
Classifier: Programming Language :: Python :: 3
Classifier: License :: OSI Approved :: MIT License
Classifier: Operating System :: OS Independent
Requires-Python: >=3.7
License-File: LICENSE
Requires-Dist: numpy
Requires-Dist: pandas
Requires-Dist: scipy
Requires-Dist: numba
